{
  "creds": {
    "noiseKey": {
      "private": {
        "type": "Buffer",
        "data": "kAbPx1go96HBvLkNz0A0u9gKCC/H4LrXckD+76qG1lE="
      },
      "public": {
        "type": "Buffer",
        "data": "4TMeDxrZugqLU80h/5L06Uqf4ovzB9ABfKKga68AUkQ="
      }
    },
    "signedIdentityKey": {
      "private": {
        "type": "Buffer",
        "data": "GJ3raIum1ZX3dQhgLkDM4pOeybew/zWIKm4vsqFls0U="
      },
      "public": {
        "type": "Buffer",
        "data": "3cYV9mt1t/Xbyv6jKKERjN3FbJxG7KaJz6Hl+u/fTy8="
      }
    },
    "signedPreKey": {
      "keyPair": {
        "private": {
          "type": "Buffer",
          "data": "MEDdwHCHMMriwi8mRRa2zDjCwGnMvaOuR/NLWAn+zUE="
        },
        "public": {
          "type": "Buffer",
          "data": "vuk4lh9UNBByFhEix+Ky4E/a+rFCKRk+DVnvZ+6G53c="
        }
      },
      "signature": {
        "type": "Buffer",
        "data": "8gMBcm13NwuP6TrwRSeYprhIQGgNm+XnFb5SMVBidjVROqqsyM/X+d6+c3e08rXu1Q7f6KKmYSCpKavZRT7jDg=="
      },
      "keyId": 1
    },
    "registrationId": 236,
    "advSecretKey": "k70oyPToUn31k+zHyXwFcUIW540jEpjH/D0Cvjt4p/0=",
    "processedHistoryMessages": [
      {
        "key": {
          "remoteJid": "62895348251900@s.whatsapp.net",
          "fromMe": true,
          "id": "A546EE59890D577C406BDE49EA3F69E3"
        },
        "messageTimestamp": 1674912073
      },
      {
        "key": {
          "remoteJid": "62895348251900@s.whatsapp.net",
          "fromMe": true,
          "id": "FA1C51586B937E2ED139DB4010C465DD"
        },
        "messageTimestamp": 1674912073
      },
      {
        "key": {
          "remoteJid": "62895348251900@s.whatsapp.net",
          "fromMe": true,
          "id": "F769604E4901CB027CBB5EACEA46B5FA"
        },
        "messageTimestamp": 1674912077
      }
    ],
    "nextPreKeyId": 31,
    "firstUnuploadedPreKeyId": 31,
    "accountSettings": {
      "unarchiveChats": false
    },
    "account": {
      "details": "CLS2tOEHEMTC1J4GGAE=",
      "accountSignatureKey": "sjUcuMVhsEYd2BVYmq1GZOIXIShj/KpfvwHNhh0DjW4=",
      "accountSignature": "pgV2/GFzK21HplvT4Va61Na8DcOTg8p7g2EfFIqdqh0x+aY3S4qFV//wF0hT5LwuTqZtMIYUtq5LFM7rbULdAQ==",
      "deviceSignature": "veD84bPndoH/wvjha2aUMpEDUjYpogTMPsf6s6hPzLDlw4iDrrufK52k5A8iycPdtDDcjl6WaTdq7/tWs0EeCg=="
    },
    "me": {
      "id": "62895348251900:72@s.whatsapp.net",
      "name": "Nivalist"
    },
    "signalIdentities": [
      {
        "identifier": {
          "name": "62895348251900:72@s.whatsapp.net",
          "deviceId": 0
        },
        "identifierKey": {
          "type": "Buffer",
          "data": "BbI1HLjFYbBGHdgVWJqtRmTiFyEoY/yqX78BzYYdA41u"
        }
      }
    ],
    "platform": "android",
    "lastAccountSyncTimestamp": 1674912160,
    "myAppStateKeyId": "AAAAAI1H"
  },
  "keys": {
    "preKeys": {
      "1": {
        "private": {
          "type": "Buffer",
          "data": "AOPftVwMfLWMVcXm4kpJCSXvBZlO9H0hToMm2z5j8mU="
        },
        "public": {
          "type": "Buffer",
          "data": "R+Mc49vNesTSa1WwlXb32gBpromcQQ8ton8m8fGHCxs="
        }
      },
      "2": {
        "private": {
          "type": "Buffer",
          "data": "+HgEzQ6E7yptPmzyKQlv7LIVO5LwAoIn9KJvWMP6Mnc="
        },
        "public": {
          "type": "Buffer",
          "data": "FpdrXDBNcsXsUT33fvWVbAEh4qIjazCb1ti0PEP2vB8="
        }
      },
      "3": {
        "private": {
          "type": "Buffer",
          "data": "ACg2DdA+0+qdRG/nE+UfUxHdq2nsYp7l7Nk5BkdpTWY="
        },
        "public": {
          "type": "Buffer",
          "data": "I0hcNc8WoG/0Q/shgMXtuZrJl6W2eif9uawwKGj7ph8="
        }
      },
      "4": {
        "private": {
          "type": "Buffer",
          "data": "UICrZ/O8tjOYaBafQc/uKgjPYZsDvetS0pJGU7Y2xXw="
        },
        "public": {
          "type": "Buffer",
          "data": "8zlOXhzg2xwnVoLWFn387GlDf4ywoT4tkrUv8UbDQTM="
        }
      },
      "5": {
        "private": {
          "type": "Buffer",
          "data": "aLFY8xTskiyXhYAB/8pz+ut0aTtq9+fHC9UlZsWZ/04="
        },
        "public": {
          "type": "Buffer",
          "data": "ZsLDjyjf/EGsFRUQbhxdnAiQNSRp33yW/wHcLQTXoXs="
        }
      },
      "6": {
        "private": {
          "type": "Buffer",
          "data": "mIkoW7yiB3En+FrWVPstY4smO33+mVnDx/dDkk2C1nk="
        },
        "public": {
          "type": "Buffer",
          "data": "dNSjWVSKOOn1Qvg2mttUNV3NBups5EY7UrlSMslOrWM="
        }
      },
      "7": {
        "private": {
          "type": "Buffer",
          "data": "eKDnRoTAkx4FTySDmkjFwCoB7Jg1EMMqqoLXHXkGd0g="
        },
        "public": {
          "type": "Buffer",
          "data": "dwTelEM9jXR73OMMirlG32IoK55fGY9o1U/ccCo3ZAg="
        }
      },
      "8": {
        "private": {
          "type": "Buffer",
          "data": "IFLpzx6Ca3KztrvXjA/lEMi43l8rFm522yYEry7/XV4="
        },
        "public": {
          "type": "Buffer",
          "data": "IrzBL5M2KKnEl9WMkJ0DZL5eHxxVpbMni5Mzpi6n8DQ="
        }
      },
      "9": {
        "private": {
          "type": "Buffer",
          "data": "uNvIEV+o4HA4BETssLBM5jKbVoStfWDB+ISrSzxLVWM="
        },
        "public": {
          "type": "Buffer",
          "data": "lo7p2GACHOznDi14YAZUfv+UX13QJcs9AVjGcDzurWw="
        }
      },
      "10": {
        "private": {
          "type": "Buffer",
          "data": "YEe3TkiAe15SKAZXb0XTUXf1BMtzcmsrqrcNexD5Jn8="
        },
        "public": {
          "type": "Buffer",
          "data": "lLVkYsma8/3DXrnEvacWUxEa61Y8K+xkm+hd5N3BeA0="
        }
      },
      "11": {
        "private": {
          "type": "Buffer",
          "data": "uD2lyfYR2vnBZGTEOsYGcQgWkW+skW+XbPGYgB7cp2g="
        },
        "public": {
          "type": "Buffer",
          "data": "sn5BnfgsyaBcGV8BCRhAfuwlplsW27ljhKshOWHjXFU="
        }
      },
      "12": {
        "private": {
          "type": "Buffer",
          "data": "oCiWDV7xyLWdJ44iYvj2NkQN/Q0gSJWYcqTjyPUvxmk="
        },
        "public": {
          "type": "Buffer",
          "data": "U54R9TRYrlbMwlElth7P2UAsvRIYmszotj6/l3RTfA4="
        }
      },
      "13": {
        "private": {
          "type": "Buffer",
          "data": "mOzMCjiEQh/Ou7knKZA7B+jcN6JLPBXIcwKnnd6KnEA="
        },
        "public": {
          "type": "Buffer",
          "data": "3+nV4rJojsRd96QizBEQvpbr+1CJipyYYNKA99l0BwE="
        }
      },
      "14": {
        "private": {
          "type": "Buffer",
          "data": "CDXdH4SO4u7681FnO/FP5U7XYfTqVt+YTvfq+5878UI="
        },
        "public": {
          "type": "Buffer",
          "data": "82tRo1Ci7K4dHdKHF8Keug5m1wz2keP24UI0ADZAdgs="
        }
      },
      "15": {
        "private": {
          "type": "Buffer",
          "data": "0Dr/9Z1b493FodChGSG2v1Gp5u9tMVbyYyNEqFGlelE="
        },
        "public": {
          "type": "Buffer",
          "data": "uXNWuVixcKYE8RwZGdI8AgLigjbnzdNmfbmm2cgyBgU="
        }
      },
      "16": {
        "private": {
          "type": "Buffer",
          "data": "+Ej32zRSrvCJZkEcFnebIlHhlxFNLg66oP6DXMMK9Xk="
        },
        "public": {
          "type": "Buffer",
          "data": "3aQCeuP3Y8n+w6kxfS/neO5GNYW/+6UM3fSIhRVZPB8="
        }
      },
      "17": {
        "private": {
          "type": "Buffer",
          "data": "WH9cOnk3oAIa4KMushirwebyeQpgL1XGtutFVu12mWw="
        },
        "public": {
          "type": "Buffer",
          "data": "7xWGu9oXQXYcLl3SRrhbSZE++O/g7F/dizY/K4rI4HE="
        }
      },
      "18": {
        "private": {
          "type": "Buffer",
          "data": "4BjaWdf95iLndLFvKkmUV8GvjmYrIaxgEgm8l/Aky3s="
        },
        "public": {
          "type": "Buffer",
          "data": "aAVVGK/SjnB3S/9o+vy49RNz1moKdaEJh/SVOwtcqQ8="
        }
      },
      "19": {
        "private": {
          "type": "Buffer",
          "data": "GOYb6Tc2RZLaVEfxJzRMgbzUZt7f4IxapPgseYc7LEc="
        },
        "public": {
          "type": "Buffer",
          "data": "SAav+s9FcVD6eJxkQkeVFmIqMXg53i0Aw/8tnCC3AXY="
        }
      },
      "20": {
        "private": {
          "type": "Buffer",
          "data": "WHTCJgqrTR/DClitt7k0nez/lhMYFap25obtySOgMlQ="
        },
        "public": {
          "type": "Buffer",
          "data": "hD4La65vMfH/R4CZ6D267s2Z65LuGYZFthyZX1MXSDk="
        }
      },
      "21": {
        "private": {
          "type": "Buffer",
          "data": "4I8jIq74vjL6GXpxh+c+FXV9OxXEJ4BD7uR9CII1V04="
        },
        "public": {
          "type": "Buffer",
          "data": "IszTmRyQ0X5vD9ywPSt75+RTGXxgil9wkwBT++AmHkA="
        }
      },
      "22": {
        "private": {
          "type": "Buffer",
          "data": "UG+pKzL7lOx+PIEKQCVIzG0DUIn3c0Wo/XAZBPA+0lw="
        },
        "public": {
          "type": "Buffer",
          "data": "7J5BwlvOJuDfqTmFfe7aK6RMdrg+LJvDARVdnNrdzCs="
        }
      },
      "23": {
        "private": {
          "type": "Buffer",
          "data": "+BD+88X85A/5mF5FfFJv7JGlhMxxQXEj74cIT3XqqkM="
        },
        "public": {
          "type": "Buffer",
          "data": "NfUmnvJcnJiQqjYeIr/AINwnUTAhtbKrBlT1/Ut6+DU="
        }
      },
      "24": {
        "private": {
          "type": "Buffer",
          "data": "4BFfSwGBJfBbPUA4AYkFVm0fOMfCB4AVkQCsF07LwUw="
        },
        "public": {
          "type": "Buffer",
          "data": "e3Tual2z22A6PgIsCXGrEI+Aur1vp5Kc4Yv99eccuWY="
        }
      },
      "25": {
        "private": {
          "type": "Buffer",
          "data": "eK24YSYkfNdUiq31RHsPrtoPGoPCL6vUe7tfTNgHBWI="
        },
        "public": {
          "type": "Buffer",
          "data": "SsK9uJQS/GybKyxq9r61k5wMkdk29vIINW+LYs+tXUg="
        }
      },
      "26": {
        "private": {
          "type": "Buffer",
          "data": "KBrE0xgrXHjj0XfFaXAYiLE8B1WWiJi++cujfKQ8RlU="
        },
        "public": {
          "type": "Buffer",
          "data": "EdZIulWX8t0KMrWHTu3KXFA5CL8UjkM/BR8wqciJDnw="
        }
      },
      "27": {
        "private": {
          "type": "Buffer",
          "data": "iGelhgYa0fGqqKk62aRB1LfqtLBPSO7E4rxmhVXhEWs="
        },
        "public": {
          "type": "Buffer",
          "data": "ZrIQ982ixK1gek8D/pIA7nopSdNgBkPB/M43fvMTpHU="
        }
      },
      "28": {
        "private": {
          "type": "Buffer",
          "data": "wMyZ2HxLCy2klulJYiiYy0qICQex7VijK+lmFUK0kVc="
        },
        "public": {
          "type": "Buffer",
          "data": "x5lP3leifIFHD9c8mwn5X/dJdlxZfacYkB9M0cQg1GM="
        }
      },
      "29": {
        "private": {
          "type": "Buffer",
          "data": "sMnwVOB6fQtMS2ovXh29WbelYxqIZgn0wVjAokTgeHc="
        },
        "public": {
          "type": "Buffer",
          "data": "wdSw5tfyYlA/Jt/I/ylC9rpWctBr0ECs7bbWHegFFB4="
        }
      },
      "30": {
        "private": {
          "type": "Buffer",
          "data": "eEi479n5vmbg4OkzRyVbnrJB6WLvCLI3BRq0mJYVrlc="
        },
        "public": {
          "type": "Buffer",
          "data": "WrINciqfOA6PwX5wPDY/Yt3j+S1o2MvTVH4tIc6gmgQ="
        }
      }
    },
    "sessions": {
      "62895348251900.0": {
        "_sessions": {
          "BdpMsC/RCWrl4bBBhc6YXsJw6esYA1PfcXUedcFq/E0C": {
            "registrationId": 1183560572,
            "currentRatchet": {
              "ephemeralKeyPair": {
                "pubKey": "BcphIN4i8BWseuvNuVSvB/nH5vi2aJ2iF9eAoIWr9gdF",
                "privKey": "wE8BO1H7VtVmQy/ZnqA7fo9uLexSXntmhHaKrmfG2lM="
              },
              "lastRemoteEphemeralKey": "BZJb06TGNBJOR2T221VH5bEvj98UZ/Toh1QqsM8/lThy",
              "previousCounter": 0,
              "rootKey": "iI/6xNtQHgVp1zFnRqZgrpTxsg8UWrY4cI/Aim9LrgI="
            },
            "indexInfo": {
              "baseKey": "BdpMsC/RCWrl4bBBhc6YXsJw6esYA1PfcXUedcFq/E0C",
              "baseKeyType": 2,
              "closed": -1,
              "used": 1674912120392,
              "created": 1674912120392,
              "remoteIdentityKey": "BbI1HLjFYbBGHdgVWJqtRmTiFyEoY/yqX78BzYYdA41u"
            },
            "_chains": {
              "BZJb06TGNBJOR2T221VH5bEvj98UZ/Toh1QqsM8/lThy": {
                "chainKey": {
                  "counter": 7,
                  "key": "q9BU+kFesXnIUyFJXtermplxDqOJyniRxTatDBdV06E="
                },
                "chainType": 2,
                "messageKeys": {}
              },
              "BcphIN4i8BWseuvNuVSvB/nH5vi2aJ2iF9eAoIWr9gdF": {
                "chainKey": {
                  "counter": 4,
                  "key": "AScCwCG4+wUYvtLZ+QMqNLriKXdeqysJYjehUxLbguo="
                },
                "chainType": 1,
                "messageKeys": {}
              }
            }
          }
        },
        "version": "v1"
      },
      "628812993018:1.0": {
        "_sessions": {
          "BUQtp53nIhAS86X9tpZL4PvFYFOD2eicUeNsBi+yj04N": {
            "registrationId": 304,
            "currentRatchet": {
              "ephemeralKeyPair": {
                "pubKey": "BeH++0vewo+qtvpyDVC+C+XTxtSF6CdkDzBFWRIJLpUW",
                "privKey": "IChsxn4OVFFUueZCDpbeW2clTixQgBNtSweH/1QIV34="
              },
              "lastRemoteEphemeralKey": "BU1tv/sV+9mgiXJuoqblrHjyhfpWafeqYufVzQAz4tU6",
              "previousCounter": 0,
              "rootKey": "O0XuJ6Hy+NoLdWC29yeY7ZoJ3n4y1h1qV8+uDzvc1H8="
            },
            "indexInfo": {
              "baseKey": "BUQtp53nIhAS86X9tpZL4PvFYFOD2eicUeNsBi+yj04N",
              "baseKeyType": 1,
              "closed": -1,
              "used": 1674912212590,
              "created": 1674912212590,
              "remoteIdentityKey": "BQaMR4Ggx83oZ/HiSfg0OaFu/wEkWfVaASVdBFoWBnA8"
            },
            "_chains": {
              "BeH++0vewo+qtvpyDVC+C+XTxtSF6CdkDzBFWRIJLpUW": {
                "chainKey": {
                  "counter": 4,
                  "key": "JYGYdF6v77R95g6ddCfR2YEAEBuNDtlm9htEZv6FrAA="
                },
                "chainType": 1,
                "messageKeys": {}
              }
            },
            "pendingPreKey": {
              "signedKeyId": 2,
              "baseKey": "BUQtp53nIhAS86X9tpZL4PvFYFOD2eicUeNsBi+yj04N",
              "preKeyId": 797
            }
          }
        },
        "version": "v1"
      },
      "628812993018.0": {
        "_sessions": {
          "BU4cHP9MoyhUOli7qaJ5EnbVTrJC0eH5FQmdUCo7W35i": {
            "registrationId": 1430816200,
            "currentRatchet": {
              "ephemeralKeyPair": {
                "pubKey": "BYdYUmCusyEJtiljxvj5asdf8IR6tzaOYqjRV9IhKyNp",
                "privKey": "YEKju63PgoqZ6i4QEQSl1/Mf2XqzP95cNHdTJ6Rgd0I="
              },
              "lastRemoteEphemeralKey": "Bfm7gv/OwRUqPxxi+s6Xam0oA9kRJ2xtWHdipSPehFxg",
              "previousCounter": 0,
              "rootKey": "+cxW1Qicx+fORZhsUAy1/prPU3jCab0kSF69DqYHeKw="
            },
            "indexInfo": {
              "baseKey": "BU4cHP9MoyhUOli7qaJ5EnbVTrJC0eH5FQmdUCo7W35i",
              "baseKeyType": 1,
              "closed": -1,
              "used": 1674912212626,
              "created": 1674912212626,
              "remoteIdentityKey": "BZT5B5SQ4GyraXLfU7FcKhm1CirrMGAtblQAoXFO57gt"
            },
            "_chains": {
              "BYdYUmCusyEJtiljxvj5asdf8IR6tzaOYqjRV9IhKyNp": {
                "chainKey": {
                  "counter": 4,
                  "key": "1sGGSaICqkhc9APkllq95y1/Y+nUdjSbmA43DzuWki0="
                },
                "chainType": 1,
                "messageKeys": {}
              }
            },
            "pendingPreKey": {
              "signedKeyId": 1,
              "baseKey": "BU4cHP9MoyhUOli7qaJ5EnbVTrJC0eH5FQmdUCo7W35i",
              "preKeyId": 1526176
            }
          }
        },
        "version": "v1"
      }
    },
    "appStateSyncKeys": {
      "AAAAAI1I": {
        "keyData": "b7r3WUv8+VszRuQztc0o7TADAT2jvhGRZxxthsMVCH0=",
        "fingerprint": {
          "rawId": 2083330867,
          "currentIndex": 1,
          "deviceIndexes": [
            0,
            1
          ]
        },
        "timestamp": "1674911875301"
      },
      "AAAAAI1G": {
        "keyData": "W0XSLaxPFCivlk3m9CZ6smkBuLdnDCX9J+I7y7Wj53E=",
        "fingerprint": {
          "rawId": 2083330866,
          "currentIndex": 1,
          "deviceIndexes": [
            0,
            1
          ]
        },
        "timestamp": "0"
      },
      "AAAAAI1H": {
        "keyData": "LlK6ngM88un2lP5YGUFA0ALDbvCWt3ivz1TZedM0NDA=",
        "fingerprint": {
          "rawId": 2083330866,
          "currentIndex": 2,
          "deviceIndexes": [
            0,
            1
          ]
        },
        "timestamp": "1674911450191"
      }
    },
    "appStateVersions": {
      "critical_block": {
        "version": 4,
        "hash": {
          "type": "Buffer",
          "data": "V+ogJaxRNUT8BRUrynlomtcOcuHmRFHCjP6179/bskl+UweQT2c9UGrR0RDrATRl7guowBvRErMSsSJlLVgalng9S56KK+6yGBuwPv+StvkecEM7ig+6znO8E5G70y/5oi1Sv3yr8fg51BcMhs21gCdlDaF13JBn44EGDWy///Y="
        },
        "indexValueMap": {
          "j7nZzQaZLvCGbbx1GQqyTBuU5b23IWI8MdAhd0nJFcc=": {
            "valueMac": {
              "type": "Buffer",
              "data": "l6euTelMmkBfsPK/Y49wDUSFb7aFslWRIIIr/YVRUpI="
            }
          },
          "3kpjpwdrnS9xpnEj7AUBbKbXq/WNBmTqBJB1MdpHFk0=": {
            "valueMac": {
              "type": "Buffer",
              "data": "IMIYOim+lLFsV5w7l7m2gowhA1x3tFD+aIVlPOnwWrY="
            }
          },
          "S6mXxap0+6pZ0awN0RQ3wanF/EygIZymx854vQn/hTo=": {
            "valueMac": {
              "type": "Buffer",
              "data": "CCqD0/f/CU2kW+oayfjBiCL62WO5sGpN3+N8Afr9l6A="
            }
          }
        }
      },
      "critical_unblock_low": {
        "version": 3,
        "hash": {
          "type": "Buffer",
          "data": "vQKV0PnNoT/Spbcpaty3OWh4A6mSYie+PtlecMOLZSUjHvFKLuTbPqQ3Itf/b1G2jobAvL8AiHvJt1dpigwjsCVq9FxZOPX3sVQu3bHbjcEoJvqvotUYtTyZ1l2BuYho8fd7g845OhapXP2BpJEbFCwjVEuwGuhRac9K9f51Pqg="
        },
        "indexValueMap": {
          "zeTsI27HpDDe29f+C3FeO2/CO8xh3msqYWS3yowLNHs=": {
            "valueMac": {
              "type": "Buffer",
              "data": "PLeJ5GR/LRaT4IllfjcKq9NlmWq0+TqLb6RS4Q1IJ8Q="
            }
          }
        }
      },
      "regular": {
        "version": 4,
        "hash": {
          "type": "Buffer",
          "data": "NcNA+/M4gVrUkcx1dIDDFZayoAJpeh1PyrW45igjO8coj9TuG+CxKkOIOtIUGakCXyBF80CgCDbCiFvraLL/vKhCZCBpfDyUtcmFbcHmCGQoCF4aFvkZ67WCYqo5Jaieq9fWY7HaklB2M1C2DvcXFg94gDblH4mpQ4VqblJ0A70="
        },
        "indexValueMap": {
          "Kza7JQEoqj6ZUd7LVhLDy9Yq4+9Wc45TIQ6aSn7O+gU=": {
            "valueMac": {
              "type": "Buffer",
              "data": "fmYAqtkTD2uKBbgE2+23xPu7n9ZDHyRJR5bKYjyAF38="
            }
          },
          "IjlKia68l/yWorF7zlp22ZLoIPp3SrjYM5swOmcUt0E=": {
            "valueMac": {
              "type": "Buffer",
              "data": "jyYx0+W1Inwag0x+UrNjb99OBUOaP3qCU1UNKFQUXM4="
            }
          }
        }
      },
      "regular_high": {
        "version": 4,
        "hash": {
          "type": "Buffer",
          "data": "DagxYLBPCW7rO/bFM8AYYAKZmU42dLizrBmo4E2fJkj3lDOCPEh+XqNxP4jAW0TrEYZY+yfGHZE3F8rWh1Sa+TgcVwgzD+lFsaN4kpG9n28DZu4XQQoIgAprstB1leOily7Q5QuOhv0+JfyXkwN7BtiG7bdejeT4KRc/LWu+7XY="
        },
        "indexValueMap": {
          "4KyzzJTGvKSFumr/1AoBB2My+5v26Gx4XKB/IMTw7hA=": {
            "valueMac": {
              "type": "Buffer",
              "data": "06BTtqUTw1SgWe4zQ2UZYBT8+Md2Vr7eqJp5wmDAp5U="
            }
          },
          "bSt66r0uKFcaRFNRCmoVTeRD7LJ3+gg4YQff/AW9lQU=": {
            "valueMac": {
              "type": "Buffer",
              "data": "jpEVRyoJTQJXbQPYEHOnwpiefcbg0r4M0w0l0Zg4T1M="
            }
          },
          "XJmuBkH2yDx6SjiU6lvzVkiJMbkpGoKpHsp3ke5K8Lw=": {
            "valueMac": {
              "type": "Buffer",
              "data": "Tr5OnPBoRXkndJhx2xFL87NRrDzzB3S/wXs3W5Dcj7A="
            }
          }
        }
      },
      "regular_low": {
        "version": 4,
        "hash": {
          "type": "Buffer",
          "data": "H/VqxlwVt+LS1gpxDmE9p1F8O82vkbpRfE2sG+N8P/X0XrMqCqa40d9UkGy4IUCW1oP5+hvl8sZU7x1n6M1DiupI/ES/Q9KjY/PswqSMCD+XyR7Ic0NyUS3Z3DdT64wNPI9EXUhc290XoJXSxS15maMKHGxHyV4dK6zVvMlf+sE="
        },
        "indexValueMap": {
          "D9FrHqmj6zv9DaSK3LlVqSwbLQjJmc1oU/u+K/Ehp6g=": {
            "valueMac": {
              "type": "Buffer",
              "data": "aqmFASSXFPo2sDQdFI9MWve49dCGYLxcjgb2POPiZ80="
            }
          },
          "+a6wYRGLmmc7Na8ND6SHIjEC41UQ3uoKyttNZ/H8ScE=": {
            "valueMac": {
              "type": "Buffer",
              "data": "QteGTjLgKPdAFWR1EKFAhluLDBiLdvTjSoGseGQS6ME="
            }
          },
          "YFGiEBlNzUsuij7xKmIdpUctdQUQGxYd8ZvpsBgaxOc=": {
            "valueMac": {
              "type": "Buffer",
              "data": "mLIu/Bv5DyQdmvhkEvBfQqVyJaT5dVJEqULb4hF0yqI="
            }
          },
          "NetcEDRGnjLrHu+GcNK8ekBfSE44eAVeYt+awDGo7/4=": {
            "valueMac": {
              "type": "Buffer",
              "data": "wLXqjZGLOcxh5zKs88vMl/LsTl0aunn6Neu6xpaGrBo="
            }
          },
          "XiZ0qDN4TVen8/wg5wTdUglIjCUnzHlRJ5vU1gvQ53Q=": {
            "valueMac": {
              "type": "Buffer",
              "data": "/T/QoxebirbPUXj7QVcUDlrKuuSi86zMD5HvTHHO1mc="
            }
          }
        }
      }
    }
  }
}